{
  "version": "16.6.1",
  "updatedAt": "2026-03-22",
  "champions": [
    {
      "name": "Aatrox",
      "id": "Aatrox",
      "positions": [
        "TOP"
      ]
    },
    {
      "name": "Ahri",
      "id": "Ahri",
      "positions": [
        "MIDDLE"
      ]
    },
    {
      "name": "Akali",
      "id": "Akali",
      "positions": [
        "MIDDLE",
        "TOP"
      ]
    },
    {
      "name": "Akshan",
      "id": "Akshan",
      "positions": [
        "MIDDLE"
      ]
    },
    {
      "name": "Alistar",
      "id": "Alistar",
      "positions": [
        "SUPPORT"
      ]
    },
    {
      "name": "Ambessa",
      "id": "Ambessa",
      "positions": [
        "TOP"
      ]
    },
    {
      "name": "Amumu",
      "id": "Amumu",
      "positions": [
        "JUNGLE",
        "SUPPORT"
      ]
    },
    {
      "name": "Anivia",
      "id": "Anivia",
      "positions": [
        "MIDDLE"
      ]
    },
    {
      "name": "Annie",
      "id": "Annie",
      "positions": [
        "MIDDLE"
      ]
    },
    {
      "name": "Aphelios",
      "id": "Aphelios",
      "positions": [
        "BOTTOM"
      ]
    },
    {
      "name": "Ashe",
      "id": "Ashe",
      "positions": [
        "BOTTOM",
        "SUPPORT"
      ]
    },
    {
      "name": "Aurelion Sol",
      "id": "AurelionSol",
      "positions": [
        "MIDDLE"
      ]
    },
    {
      "name": "Aurora",
      "id": "Aurora",
      "positions": [
        "MIDDLE",
        "TOP"
      ]
    },
    {
      "name": "Azir",
      "id": "Azir",
      "positions": [
        "MIDDLE"
      ]
    },
    {
      "name": "Bard",
      "id": "Bard",
      "positions": [
        "SUPPORT"
      ]
    },
    {
      "name": "Bel'Veth",
      "id": "Belveth",
      "positions": [
        "JUNGLE"
      ]
    },
    {
      "name": "Blitzcrank",
      "id": "Blitzcrank",
      "positions": [
        "SUPPORT"
      ]
    },
    {
      "name": "Brand",
      "id": "Brand",
      "positions": [
        "JUNGLE",
        "MIDDLE",
        "SUPPORT"
      ]
    },
    {
      "name": "Braum",
      "id": "Braum",
      "positions": [
        "SUPPORT"
      ]
    },
    {
      "name": "Briar",
      "id": "Briar",
      "positions": [
        "JUNGLE"
      ]
    },
    {
      "name": "Caitlyn",
      "id": "Caitlyn",
      "positions": [
        "BOTTOM"
      ]
    },
    {
      "name": "Camille",
      "id": "Camille",
      "positions": [
        "SUPPORT",
        "TOP"
      ]
    },
    {
      "name": "Cassiopeia",
      "id": "Cassiopeia",
      "positions": [
        "MIDDLE"
      ]
    },
    {
      "name": "Cho'Gath",
      "id": "Chogath",
      "positions": [
        "TOP"
      ]
    },
    {
      "name": "Corki",
      "id": "Corki",
      "positions": [
        "MIDDLE"
      ]
    },
    {
      "name": "Darius",
      "id": "Darius",
      "positions": [
        "TOP"
      ]
    },
    {
      "name": "Diana",
      "id": "Diana",
      "positions": [
        "JUNGLE",
        "MIDDLE"
      ]
    },
    {
      "name": "Dr. Mundo",
      "id": "DrMundo",
      "positions": [
        "TOP"
      ]
    },
    {
      "name": "Draven",
      "id": "Draven",
      "positions": [
        "BOTTOM"
      ]
    },
    {
      "name": "Ekko",
      "id": "Ekko",
      "positions": [
        "JUNGLE",
        "MIDDLE"
      ]
    },
    {
      "name": "Elise",
      "id": "Elise",
      "positions": [
        "JUNGLE"
      ]
    },
    {
      "name": "Evelynn",
      "id": "Evelynn",
      "positions": [
        "JUNGLE"
      ]
    },
    {
      "name": "Ezreal",
      "id": "Ezreal",
      "positions": [
        "BOTTOM"
      ]
    },
    {
      "name": "Fiddlesticks",
      "id": "Fiddlesticks",
      "positions": [
        "JUNGLE"
      ]
    },
    {
      "name": "Fiora",
      "id": "Fiora",
      "positions": [
        "TOP"
      ]
    },
    {
      "name": "Fizz",
      "id": "Fizz",
      "positions": [
        "MIDDLE"
      ]
    },
    {
      "name": "Galio",
      "id": "Galio",
      "positions": [
        "MIDDLE",
        "SUPPORT"
      ]
    },
    {
      "name": "Gangplank",
      "id": "Gangplank",
      "positions": [
        "TOP"
      ]
    },
    {
      "name": "Garen",
      "id": "Garen",
      "positions": [
        "TOP"
      ]
    },
    {
      "name": "Gnar",
      "id": "Gnar",
      "positions": [
        "TOP"
      ]
    },
    {
      "name": "Gragas",
      "id": "Gragas",
      "positions": [
        "JUNGLE",
        "MIDDLE",
        "TOP"
      ]
    },
    {
      "name": "Graves",
      "id": "Graves",
      "positions": [
        "JUNGLE"
      ]
    },
    {
      "name": "Gwen",
      "id": "Gwen",
      "positions": [
        "JUNGLE",
        "TOP"
      ]
    },
    {
      "name": "Hecarim",
      "id": "Hecarim",
      "positions": [
        "JUNGLE"
      ]
    },
    {
      "name": "Heimerdinger",
      "id": "Heimerdinger",
      "positions": [
        "MIDDLE",
        "SUPPORT",
        "TOP"
      ]
    },
    {
      "name": "Hwei",
      "id": "Hwei",
      "positions": [
        "MIDDLE",
        "SUPPORT"
      ]
    },
    {
      "name": "Illaoi",
      "id": "Illaoi",
      "positions": [
        "TOP"
      ]
    },
    {
      "name": "Irelia",
      "id": "Irelia",
      "positions": [
        "MIDDLE",
        "TOP"
      ]
    },
    {
      "name": "Ivern",
      "id": "Ivern",
      "positions": [
        "JUNGLE"
      ]
    },
    {
      "name": "Janna",
      "id": "Janna",
      "positions": [
        "SUPPORT"
      ]
    },
    {
      "name": "Jarvan IV",
      "id": "JarvanIV",
      "positions": [
        "JUNGLE"
      ]
    },
    {
      "name": "Jax",
      "id": "Jax",
      "positions": [
        "JUNGLE",
        "TOP"
      ]
    },
    {
      "name": "Jayce",
      "id": "Jayce",
      "positions": [
        "MIDDLE",
        "TOP"
      ]
    },
    {
      "name": "Jhin",
      "id": "Jhin",
      "positions": [
        "BOTTOM"
      ]
    },
    {
      "name": "Jinx",
      "id": "Jinx",
      "positions": [
        "BOTTOM"
      ]
    },
    {
      "name": "K'Sante",
      "id": "KSante",
      "positions": [
        "TOP"
      ]
    },
    {
      "name": "Kai'Sa",
      "id": "Kaisa",
      "positions": [
        "BOTTOM"
      ]
    },
    {
      "name": "Kalista",
      "id": "Kalista",
      "positions": [
        "BOTTOM"
      ]
    },
    {
      "name": "Karma",
      "id": "Karma",
      "positions": [
        "MIDDLE",
        "SUPPORT",
        "TOP"
      ]
    },
    {
      "name": "Karthus",
      "id": "Karthus",
      "positions": [
        "JUNGLE"
      ]
    },
    {
      "name": "Kassadin",
      "id": "Kassadin",
      "positions": [
        "MIDDLE"
      ]
    },
    {
      "name": "Katarina",
      "id": "Katarina",
      "positions": [
        "MIDDLE"
      ]
    },
    {
      "name": "Kayle",
      "id": "Kayle",
      "positions": [
        "TOP"
      ]
    },
    {
      "name": "Kayn",
      "id": "Kayn",
      "positions": [
        "JUNGLE"
      ]
    },
    {
      "name": "Kennen",
      "id": "Kennen",
      "positions": [
        "TOP"
      ]
    },
    {
      "name": "Kha'Zix",
      "id": "Khazix",
      "positions": [
        "JUNGLE"
      ]
    },
    {
      "name": "Kindred",
      "id": "Kindred",
      "positions": [
        "JUNGLE"
      ]
    },
    {
      "name": "Kled",
      "id": "Kled",
      "positions": [
        "TOP"
      ]
    },
    {
      "name": "Kog'Maw",
      "id": "KogMaw",
      "positions": [
        "BOTTOM"
      ]
    },
    {
      "name": "LeBlanc",
      "id": "Leblanc",
      "positions": [
        "MIDDLE"
      ]
    },
    {
      "name": "Lee Sin",
      "id": "LeeSin",
      "positions": [
        "JUNGLE"
      ]
    },
    {
      "name": "Leona",
      "id": "Leona",
      "positions": [
        "SUPPORT"
      ]
    },
    {
      "name": "Lillia",
      "id": "Lillia",
      "positions": [
        "JUNGLE"
      ]
    },
    {
      "name": "Lissandra",
      "id": "Lissandra",
      "positions": [
        "MIDDLE"
      ]
    },
    {
      "name": "Lucian",
      "id": "Lucian",
      "positions": [
        "BOTTOM"
      ]
    },
    {
      "name": "Lulu",
      "id": "Lulu",
      "positions": [
        "SUPPORT"
      ]
    },
    {
      "name": "Lux",
      "id": "Lux",
      "positions": [
        "MIDDLE",
        "SUPPORT"
      ]
    },
    {
      "name": "Malphite",
      "id": "Malphite",
      "positions": [
        "MIDDLE",
        "SUPPORT",
        "TOP"
      ]
    },
    {
      "name": "Malzahar",
      "id": "Malzahar",
      "positions": [
        "MIDDLE"
      ]
    },
    {
      "name": "Maokai",
      "id": "Maokai",
      "positions": [
        "JUNGLE",
        "SUPPORT"
      ]
    },
    {
      "name": "Master Yi",
      "id": "MasterYi",
      "positions": [
        "JUNGLE"
      ]
    },
    {
      "name": "Mel",
      "id": "Mel",
      "positions": [
        "MIDDLE",
        "SUPPORT"
      ]
    },
    {
      "name": "Milio",
      "id": "Milio",
      "positions": [
        "SUPPORT"
      ]
    },
    {
      "name": "Miss Fortune",
      "id": "MissFortune",
      "positions": [
        "BOTTOM"
      ]
    },
    {
      "name": "Mordekaiser",
      "id": "Mordekaiser",
      "positions": [
        "TOP"
      ]
    },
    {
      "name": "Morgana",
      "id": "Morgana",
      "positions": [
        "SUPPORT"
      ]
    },
    {
      "name": "Naafiri",
      "id": "Naafiri",
      "positions": [
        "MIDDLE"
      ]
    },
    {
      "name": "Nami",
      "id": "Nami",
      "positions": [
        "SUPPORT"
      ]
    },
    {
      "name": "Nasus",
      "id": "Nasus",
      "positions": [
        "TOP"
      ]
    },
    {
      "name": "Nautilus",
      "id": "Nautilus",
      "positions": [
        "SUPPORT"
      ]
    },
    {
      "name": "Neeko",
      "id": "Neeko",
      "positions": [
        "MIDDLE",
        "SUPPORT"
      ]
    },
    {
      "name": "Nidalee",
      "id": "Nidalee",
      "positions": [
        "JUNGLE"
      ]
    },
    {
      "name": "Nilah",
      "id": "Nilah",
      "positions": [
        "BOTTOM"
      ]
    },
    {
      "name": "Nocturne",
      "id": "Nocturne",
      "positions": [
        "JUNGLE"
      ]
    },
    {
      "name": "Nunu",
      "id": "Nunu",
      "positions": [
        "JUNGLE"
      ]
    },
    {
      "name": "Olaf",
      "id": "Olaf",
      "positions": [
        "TOP"
      ]
    },
    {
      "name": "Orianna",
      "id": "Orianna",
      "positions": [
        "MIDDLE"
      ]
    },
    {
      "name": "Ornn",
      "id": "Ornn",
      "positions": [
        "TOP"
      ]
    },
    {
      "name": "Pantheon",
      "id": "Pantheon",
      "positions": [
        "JUNGLE",
        "MIDDLE",
        "SUPPORT",
        "TOP"
      ]
    },
    {
      "name": "Poppy",
      "id": "Poppy",
      "positions": [
        "JUNGLE",
        "TOP"
      ]
    },
    {
      "name": "Pyke",
      "id": "Pyke",
      "positions": [
        "SUPPORT"
      ]
    },
    {
      "name": "Qiyana",
      "id": "Qiyana",
      "positions": [
        "MIDDLE"
      ]
    },
    {
      "name": "Quinn",
      "id": "Quinn",
      "positions": [
        "TOP"
      ]
    },
    {
      "name": "Rakan",
      "id": "Rakan",
      "positions": [
        "SUPPORT"
      ]
    },
    {
      "name": "Rammus",
      "id": "Rammus",
      "positions": [
        "JUNGLE"
      ]
    },
    {
      "name": "Rek'Sai",
      "id": "RekSai",
      "positions": [
        "JUNGLE"
      ]
    },
    {
      "name": "Rell",
      "id": "Rell",
      "positions": [
        "SUPPORT"
      ]
    },
    {
      "name": "Renata Glasc",
      "id": "Renata",
      "positions": [
        "SUPPORT"
      ]
    },
    {
      "name": "Renekton",
      "id": "Renekton",
      "positions": [
        "TOP"
      ]
    },
    {
      "name": "Rengar",
      "id": "Rengar",
      "positions": [
        "JUNGLE",
        "TOP"
      ]
    },
    {
      "name": "Riven",
      "id": "Riven",
      "positions": [
        "TOP"
      ]
    },
    {
      "name": "Rumble",
      "id": "Rumble",
      "positions": [
        "MIDDLE",
        "TOP"
      ]
    },
    {
      "name": "Ryze",
      "id": "Ryze",
      "positions": [
        "MIDDLE"
      ]
    },
    {
      "name": "Samira",
      "id": "Samira",
      "positions": [
        "BOTTOM"
      ]
    },
    {
      "name": "Sejuani",
      "id": "Sejuani",
      "positions": [
        "JUNGLE"
      ]
    },
    {
      "name": "Senna",
      "id": "Senna",
      "positions": [
        "BOTTOM",
        "SUPPORT"
      ]
    },
    {
      "name": "Seraphine",
      "id": "Seraphine",
      "positions": [
        "BOTTOM",
        "SUPPORT"
      ]
    },
    {
      "name": "Sett",
      "id": "Sett",
      "positions": [
        "TOP"
      ]
    },
    {
      "name": "Shaco",
      "id": "Shaco",
      "positions": [
        "JUNGLE",
        "SUPPORT"
      ]
    },
    {
      "name": "Shen",
      "id": "Shen",
      "positions": [
        "SUPPORT",
        "TOP"
      ]
    },
    {
      "name": "Shyvana",
      "id": "Shyvana",
      "positions": [
        "JUNGLE"
      ]
    },
    {
      "name": "Singed",
      "id": "Singed",
      "positions": [
        "TOP"
      ]
    },
    {
      "name": "Sion",
      "id": "Sion",
      "positions": [
        "TOP"
      ]
    },
    {
      "name": "Sivir",
      "id": "Sivir",
      "positions": [
        "BOTTOM"
      ]
    },
    {
      "name": "Skarner",
      "id": "Skarner",
      "positions": [
        "JUNGLE",
        "TOP"
      ]
    },
    {
      "name": "Smolder",
      "id": "Smolder",
      "positions": [
        "BOTTOM",
        "MIDDLE",
        "TOP"
      ]
    },
    {
      "name": "Sona",
      "id": "Sona",
      "positions": [
        "SUPPORT"
      ]
    },
    {
      "name": "Soraka",
      "id": "Soraka",
      "positions": [
        "SUPPORT"
      ]
    },
    {
      "name": "Swain",
      "id": "Swain",
      "positions": [
        "BOTTOM",
        "MIDDLE",
        "SUPPORT"
      ]
    },
    {
      "name": "Sylas",
      "id": "Sylas",
      "positions": [
        "MIDDLE",
        "TOP"
      ]
    },
    {
      "name": "Syndra",
      "id": "Syndra",
      "positions": [
        "MIDDLE"
      ]
    },
    {
      "name": "Tahm Kench",
      "id": "TahmKench",
      "positions": [
        "SUPPORT",
        "TOP"
      ]
    },
    {
      "name": "Taliyah",
      "id": "Taliyah",
      "positions": [
        "JUNGLE",
        "MIDDLE"
      ]
    },
    {
      "name": "Talon",
      "id": "Talon",
      "positions": [
        "JUNGLE"
      ]
    },
    {
      "name": "Taric",
      "id": "Taric",
      "positions": [
        "MIDDLE",
        "SUPPORT"
      ]
    },
    {
      "name": "Teemo",
      "id": "Teemo",
      "positions": [
        "JUNGLE",
        "SUPPORT",
        "TOP"
      ]
    },
    {
      "name": "Thresh",
      "id": "Thresh",
      "positions": [
        "SUPPORT"
      ]
    },
    {
      "name": "Tristana",
      "id": "Tristana",
      "positions": [
        "BOTTOM",
        "MIDDLE"
      ]
    },
    {
      "name": "Trundle",
      "id": "Trundle",
      "positions": [
        "JUNGLE",
        "TOP"
      ]
    },
    {
      "name": "Tryndamere",
      "id": "Tryndamere",
      "positions": [
        "TOP"
      ]
    },
    {
      "name": "Twisted Fate",
      "id": "TwistedFate",
      "positions": [
        "BOTTOM",
        "MIDDLE",
        "TOP"
      ]
    },
    {
      "name": "Twitch",
      "id": "Twitch",
      "positions": [
        "BOTTOM",
        "SUPPORT"
      ]
    },
    {
      "name": "Udyr",
      "id": "Udyr",
      "positions": [
        "JUNGLE",
        "TOP"
      ]
    },
    {
      "name": "Urgot",
      "id": "Urgot",
      "positions": [
        "TOP"
      ]
    },
    {
      "name": "Varus",
      "id": "Varus",
      "positions": [
        "BOTTOM"
      ]
    },
    {
      "name": "Vayne",
      "id": "Vayne",
      "positions": [
        "BOTTOM",
        "TOP"
      ]
    },
    {
      "name": "Veigar",
      "id": "Veigar",
      "positions": [
        "MIDDLE",
        "SUPPORT"
      ]
    },
    {
      "name": "Vel'Koz",
      "id": "Velkoz",
      "positions": [
        "MIDDLE",
        "SUPPORT"
      ]
    },
    {
      "name": "Vex",
      "id": "Vex",
      "positions": [
        "MIDDLE"
      ]
    },
    {
      "name": "Vi",
      "id": "Vi",
      "positions": [
        "JUNGLE"
      ]
    },
    {
      "name": "Viego",
      "id": "Viego",
      "positions": [
        "JUNGLE"
      ]
    },
    {
      "name": "Viktor",
      "id": "Viktor",
      "positions": [
        "MIDDLE"
      ]
    },
    {
      "name": "Vladimir",
      "id": "Vladimir",
      "positions": [
        "MIDDLE",
        "TOP"
      ]
    },
    {
      "name": "Volibear",
      "id": "Volibear",
      "positions": [
        "JUNGLE",
        "TOP"
      ]
    },
    {
      "name": "Warwick",
      "id": "Warwick",
      "positions": [
        "JUNGLE",
        "TOP"
      ]
    },
    {
      "name": "Wukong",
      "id": "MonkeyKing",
      "positions": [
        "JUNGLE",
        "TOP"
      ]
    },
    {
      "name": "Xayah",
      "id": "Xayah",
      "positions": [
        "BOTTOM"
      ]
    },
    {
      "name": "Xerath",
      "id": "Xerath",
      "positions": [
        "MIDDLE",
        "SUPPORT"
      ]
    },
    {
      "name": "Xin Zhao",
      "id": "XinZhao",
      "positions": [
        "JUNGLE"
      ]
    },
    {
      "name": "Yasuo",
      "id": "Yasuo",
      "positions": [
        "BOTTOM",
        "MIDDLE",
        "TOP"
      ]
    },
    {
      "name": "Yone",
      "id": "Yone",
      "positions": [
        "MIDDLE",
        "TOP"
      ]
    },
    {
      "name": "Yorick",
      "id": "Yorick",
      "positions": [
        "TOP"
      ]
    },
    {
      "name": "Yunara",
      "id": "Yunara",
      "positions": [
        "BOTTOM"
      ]
    },
    {
      "name": "Yuumi",
      "id": "Yuumi",
      "positions": [
        "SUPPORT"
      ]
    },
    {
      "name": "Zaahen",
      "id": "Zaahen",
      "positions": []
    },
    {
      "name": "Zac",
      "id": "Zac",
      "positions": [
        "JUNGLE",
        "SUPPORT",
        "TOP"
      ]
    },
    {
      "name": "Zed",
      "id": "Zed",
      "positions": [
        "JUNGLE",
        "MIDDLE"
      ]
    },
    {
      "name": "Zeri",
      "id": "Zeri",
      "positions": [
        "BOTTOM"
      ]
    },
    {
      "name": "Ziggs",
      "id": "Ziggs",
      "positions": [
        "BOTTOM",
        "MIDDLE"
      ]
    },
    {
      "name": "Zilean",
      "id": "Zilean",
      "positions": [
        "SUPPORT"
      ]
    },
    {
      "name": "Zoe",
      "id": "Zoe",
      "positions": [
        "MIDDLE"
      ]
    },
    {
      "name": "Zyra",
      "id": "Zyra",
      "positions": [
        "SUPPORT"
      ]
    }
  ]
}
